banking_tools/__init__.py
banking_tools/cosecha/__init__.py
banking_tools/cosecha/cosecha_agg.py
banking_tools/cosecha/cosecha_rfm.py
example/__init__.py
banking_tools-0.1.dist-info/LICENSE
banking_tools-0.1.dist-info/METADATA
banking_tools-0.1.dist-info/WHEEL
banking_tools-0.1.dist-info/top_level.txt
banking_tools-0.1.dist-info/RECORD
